django_wechat_feedback-0.3.dist-info/DESCRIPTION.rst
django_wechat_feedback-0.3.dist-info/METADATA
django_wechat_feedback-0.3.dist-info/RECORD
django_wechat_feedback-0.3.dist-info/WHEEL
django_wechat_feedback-0.3.dist-info/metadata.json
django_wechat_feedback-0.3.dist-info/top_level.txt
feedback/__init__.py
feedback/admin.py
feedback/apps.py
feedback/models.py
feedback/tests.py
feedback/urls.py
feedback/views.py
feedback/templates/feedback/base.html
feedback/templates/feedback/feedback_form.html
feedback/templates/feedback/success.html
